Workbook

Sheet 1_營收與訂閱預測
A1: 星橋科技 2026 年度產品營收與付費訂閱增長試算表
A2: 單位：新台幣 (NTD) | 編制日期：2026-03-31 | 編制：財務規劃部 (FP&A)
A4: 產品項目 | B4: 定價方案 (年費) | C4: Q1 實際 | D4: Q2 預測 | E4: Q3 預測 | F4: Q4 預測 | G4: 全年預計總額 | H4: 佔比 (%)
A5: OmniFlow 個人專業版 (Pro) | B5: 4800 | C5: 1200000 | D5: 1920000 | E5: 2880000 | F5: 3600000 | G5: =SUM(C5:F5) | H5: =G5/$G$10
A6: OmniFlow 團隊協作版 (Team) | B6: 28000 | C6: 2240000 | D6: 3360000 | E6: 4480000 | F6: 5600000 | G6: =SUM(C6:F6) | H6: =G6/$G$10
A7: OmniFlow 企業定製沙盒 (Enterprise) | B7: 180000 | C7: 3600000 | D7: 5400000 | E7: 7200000 | F7: 9000000 | G7: =SUM(C7:F7) | H7: =G7/$G$10
A8: 專業顧問與私有化導入服務 | B8: 350000 | C8: 1050000 | D8: 1400000 | E8: 1750000 | F8: 2100000 | G8: =SUM(C8:F8) | H8: =G8/$G$10
A9: 客製化 API 呼叫增購額度 | B9: 12 | C9: 450000 | D9: 680000 | E9: 950000 | F9: 1420000 | G9: =SUM(C9:F9) | H9: =G9/$G$10
A10: 合計營業收入總額 (Total Revenue) | B10: - | C10: =SUM(C5:C9) | D10: =SUM(D5:D9) | E10: =SUM(E5:E9) | F10: =SUM(F5:F9) | G10: =SUM(G5:G9) | H10: =SUM(H5:H9)

Sheet 2_營業費用與行銷預算
A1: 星橋科技 2026 年度各部門營業支出與活動預算明細
A3: 費用類別 | B3: 預算細項 | C3: 負責部門 | D3: Q1 預算 | E3: Q2 預算 | F3: Q3 預算 | G3: Q4 預算 | H3: 全年支出總計
A4: 研發人力 | B4: 軟體工程師與 AI 算力研發團隊薪酬 | C4: 研發部 | D4: 3200000 | E4: 3500000 | F4: 3800000 | G4: 4200000 | H4: =SUM(D4:G4)
A5: 雲端算力 | B5: AWS / Google Cloud / LLM API 呼叫費 | C5: 架構組 | D5: 1100000 | E5: 1600000 | F5: 2200000 | G5: 2800000 | H5: =SUM(D5:G5)
A6: 發表會活動 | B6: 旗艦線上直播發表會、場地、製作費 | C6: 行銷部 | D6: 450000 | E6: 1250000 | F6: 300000 | G6: 600000 | H6: =SUM(D6:G6)
A7: 數位廣告投放 | B7: Google Ads / LinkedIn 企業精準受眾獲客 | C7: 行銷部 | D7: 800000 | E7: 1500000 | F7: 1800000 | G7: 2000000 | H7: =SUM(D7:G7)
A8: 銷售獎金與人事 | B8: 企業業務拓展業務經理底薪與佣金 | C8: 業務部 | D8: 1200000 | E8: 1500000 | F8: 1900000 | G8: 2400000 | H8: =SUM(D8:G8)
A9: 行政與管理 | B9: 辦公室租金、資安合規審計與法律諮詢 | C9: 行政法務 | D9: 650000 | E9: 700000 | F9: 750000 | G9: 800000 | H9: =SUM(D9:G9)
A10: 營業支出合計 (Total OPEX) | B10: - | C10: - | D10: =SUM(D4:D9) | E10: =SUM(E4:E9) | F10: =SUM(F4:F9) | G10: =SUM(G4:G9) | H10: =SUM(H4:H9)

Sheet 3_綜合損益試算表 (P&L)
A1: 星橋科技 2026 年度預估損益表 (Income Statement P&L)
A3: 財務科目 | B3: Q1 預估 | C3: Q2 預估 | D3: Q3 預估 | E3: Q4 預估 | F3: 2026 全年合計 | G3: 營收比率 (%)
A4: 營業收入 (Revenue) | B4: ='1_營收與訂閱預測'!C10 | C4: ='1_營收與訂閱預測'!D10 | D4: ='1_營收與訂閱預測'!E10 | E4: ='1_營收與訂閱預測'!F10 | F4: ='1_營收與訂閱預測'!G10 | G4: =F4/$F$4
A5: 營業成本 (COGS - 雲端算力與串接) | B5: ='2_營業費用與行銷預算'!D5 | C5: ='2_營業費用與行銷預算'!E5 | D5: ='2_營業費用與行銷預算'!F5 | E5: ='2_營業費用與行銷預算'!G5 | F5: ='2_營業費用與行銷預算'!H5 | G5: =F5/$F$4
A6: 營業毛利 (Gross Profit) | B6: =B4-B5 | C6: =C4-C5 | D6: =D4-D5 | E6: =E4-E5 | F6: =F4-F5 | G6: =F6/$F$4
A7: 營業費用 (OPEX - 研發/行銷/人事/行政) | B7: ='2_營業費用與行銷預算'!D10-B5 | C7: ='2_營業費用與行銷預算'!E10-C5 | D7: ='2_營業費用與行銷預算'!F10-D5 | E7: ='2_營業費用與行銷預算'!G10-E5 | F7: ='2_營業費用與行銷預算'!H10-F5 | G7: =F7/$F$4
A8: 營業淨利 (Operating Income) | B8: =B6-B7 | C8: =C6-C7 | D8: =D6-D7 | E8: =E6-E7 | F8: =F6-F7 | G8: =F8/$F$4
A9: 稅前折舊攤銷前獲利 (EBITDA) | B9: =B8+350000 | C9: =C8+380000 | D9: =D8+420000 | E9: =E8+450000 | F9: =F8+1600000 | G9: =F9/$F$4

Sheet 4_情境敏感度分析
A1: 2026 年度營運三種情境敏感度模擬分析 (Scenario Simulation)
A3: 分析情境 | B3: 付費轉換率假定 | C3: 預估年度營收 (ARR) | D3: 預估年度總支出 | E3: 預估 EBITDA | F3: 損益平衡狀態
A4: 保守情境 (Conservative) | B4: 付費轉換率 1.8% (市場保守/預算縮編) | C4: ='3_綜合損益試算表 (P&L)'!F4*0.75 | D4: ='3_綜合損益試算表 (P&L)'!F7*0.85 | E4: =C4-D4 | F4: 延遲至 Q4 損平
A5: 基準情境 (Base Case - 本案) | B5: 付費轉換率 2.8% (正常發表與穩健增長) | C5: ='3_綜合損益試算表 (P&L)'!F4 | D5: ='3_綜合損益試算表 (P&L)'!F7 | E5: =C5-D5 | F5: 預計 Q2 損益兩平
A6: 樂觀情境 (Optimistic) | B6: 付費轉換率 4.5% (發表會爆發/口碑擴散) | C6: ='3_綜合損益試算表 (P&L)'!F4*1.35 | D6: ='3_綜合損益試算表 (P&L)'!F7*1.10 | E6: =C6-D6 | F6: Q1 即獲利並加速擴張
