Workbook

Sheet KPI_營運分析儀表板
A1: 2026 年第一季全通路營運績效與決策儀表板 (Executive KPI Dashboard)
A2: 統計區間：2026/01/01 ~ 2026/03/31 ｜ 資料來源：銷售明細表與產品主檔 ｜ 幣別：NTD
A4: 全季總營業收入 | C4: 全季商品總毛利 | E4: 全通路平均毛利率 | G4: 全通路退貨率
A5: =銷售流水明細!H23 | C5: =銷售流水明細!K23 | E5: =銷售流水明細!L23 | G5: =COUNTIF(銷售流水明細!M3:M22,"已退貨")/COUNTA(銷售流水明細!A3:A22)
A7: 【各銷售通路營業績效與退貨損耗對比表】
A8: 通路排名 | B8: 銷售通路名稱 | C8: 訂單筆數 | D8: 銷售數量 | E8: 通路總營收(NT$) | F8: 通路總毛利(NT$) | G8: 退貨訂單數 | H8: 通路退貨率
A9: 第 1 名 | B9: Momo購物網 | C9: =COUNTIF(銷售流水明細!$C$3:$C$22, "Momo購物網") | D9: =SUMIFS(銷售流水明細!$F$3:$F$22, 銷售流水明細!$C$3:$C$22, "Momo購物網") | E9: =SUMIFS(銷售流水明細!$H$3:$H$22, 銷售流水明細!$C$3:$C$22, "Momo購物網") | F9: =SUMIFS(銷售流水明細!$K$3:$K$22, 銷售流水明細!$C$3:$C$22, "Momo購物網") | G9: =COUNTIFS(銷售流水明細!$C$3:$C$22, "Momo購物網", 銷售流水明細!$M$3:$M$22, "已退貨") | H9: =G9/C9
A10: 第 2 名 | B10: 官網商城 | C10: =COUNTIF(銷售流水明細!$C$3:$C$22, "官網商城") | D10: =SUMIFS(銷售流水明細!$F$3:$F$22, 銷售流水明細!$C$3:$C$22, "官網商城") | E10: =SUMIFS(銷售流水明細!$H$3:$H$22, 銷售流水明細!$C$3:$C$22, "官網商城") | F10: =SUMIFS(銷售流水明細!$K$3:$K$22, 銷售流水明細!$C$3:$C$22, "官網商城") | G10: =COUNTIFS(銷售流水明細!$C$3:$C$22, "官網商城", 銷售流水明細!$M$3:$M$22, "已退貨") | H10: =G10/C10
A11: 第 3 名 | B11: 台北信義門市 | C11: =COUNTIF(銷售流水明細!$C$3:$C$22, "台北信義門市") | D11: =SUMIFS(銷售流水明細!$F$3:$F$22, 銷售流水明細!$C$3:$C$22, "台北信義門市") | E11: =SUMIFS(銷售流水明細!$H$3:$H$22, 銷售流水明細!$C$3:$C$22, "台北信義門市") | F11: =SUMIFS(銷售流水明細!$K$3:$K$22, 銷售流水明細!$C$3:$C$22, "台北信義門市") | G11: =COUNTIFS(銷售流水明細!$C$3:$C$22, "台北信義門市", 銷售流水明細!$M$3:$M$22, "已退貨") | H11: =G11/C11
A12: 第 4 名 | B12: 台中旗艦門市 | C12: =COUNTIF(銷售流水明細!$C$3:$C$22, "台中旗艦門市") | D12: =SUMIFS(銷售流水明細!$F$3:$F$22, 銷售流水明細!$C$3:$C$22, "台中旗艦門市") | E12: =SUMIFS(銷售流水明細!$H$3:$H$22, 銷售流水明細!$C$3:$C$22, "台中旗艦門市") | F12: =SUMIFS(銷售流水明細!$K$3:$K$22, 銷售流水明細!$C$3:$C$22, "台中旗艦門市") | G12: =COUNTIFS(銷售流水明細!$C$3:$C$22, "台中旗艦門市", 銷售流水明細!$M$3:$M$22, "已退貨") | H12: =G12/C12
A13: 第 5 名 | B13: 蝦皮商城 | C13: =COUNTIF(銷售流水明細!$C$3:$C$22, "蝦皮商城") | D13: =SUMIFS(銷售流水明細!$F$3:$F$22, 銷售流水明細!$C$3:$C$22, "蝦皮商城") | E13: =SUMIFS(銷售流水明細!$H$3:$H$22, 銷售流水明細!$C$3:$C$22, "蝦皮商城") | F13: =SUMIFS(銷售流水明細!$K$3:$K$22, 銷售流水明細!$C$3:$C$22, "蝦皮商城") | G13: =COUNTIFS(銷售流水明細!$C$3:$C$22, "蝦皮商城", 銷售流水明細!$M$3:$M$22, "已退貨") | H13: =G13/C13
A14: 全通路合計 | C14: =SUM(C9:C13) | D14: =SUM(D9:D13) | E14: =SUM(E9:E13) | F14: =SUM(F9:F13) | G14: =SUM(G9:G13) | H14: =G14/C14

Sheet 產品規格主檔
A1: 企業產品規格與成本定價主檔 (Product Master)
A2: 產品編號 | B2: 產品品名 | C2: 商品類別 | D2: 建議售價(NT$) | E2: 進貨單位成本(NT$) | F2: 安全毛利率門檻
A3: SKU-A101 | B3: 極簡人體工學滑鼠墊 | C3: 辦公周邊 | D3: 1580 | E3: 620 | F3: 0.5
A4: SKU-A102 | B4: 無線雙模機械鍵盤 | C4: 辦公周邊 | D4: 3880 | E4: 1850 | F4: 0.45
A5: SKU-B201 | B5: 主動降噪藍牙耳罩耳機 | C5: 影音設備 | D5: 2280 | E5: 1100 | F5: 0.45
A6: SKU-B202 | B6: 4K超高清串流視訊鏡頭 | C6: 影音設備 | D6: 4500 | E6: 2100 | F6: 0.5
A7: SKU-C301 | B7: Type-C多功能擴充基座 | C7: 線材配件 | D7: 890 | E7: 380 | F7: 0.5
A8: SKU-C302 | B8: 100W氮化鎵GaN快充頭 | C8: 線材配件 | D8: 1250 | E8: 550 | F8: 0.5

Sheet 銷售流水明細
A1: 2026 年第一季全通路銷售明細流水帳 (Sales Transactions)
A2: 訂單編號 | B2: 銷售日期 | C2: 銷售通路 | D2: 產品編號 | E2: 產品品名 | F2: 銷售數量 | G2: 實收單價 | H2: 訂單金額 | I2: 單位進貨成本 | J2: 總成本 | K2: 毛利金額 | L2: 毛利率 | M2: 交易狀態 | N2: 備註說明
A3: ORD-2026-001 | B3: 2026-01-05 | C3: 官網商城 | D3: SKU-A101 | E3: =XLOOKUP(D3,產品規格主檔!$A$3:$A$8,產品規格主檔!$B$3:$B$8) | F3: 3 | G3: 1580 | H3: =F3*G3 | I3: =XLOOKUP(D3,產品規格主檔!$A$3:$A$8,產品規格主檔!$E$3:$E$8) | J3: =F3*I3 | K3: =H3-J3 | L3: =K3/H3 | M3: 正常完成 | N3: 免運優惠
A4: ORD-2026-002 | B4: 2026-01-07 | C4: 台北信義門市 | D4: SKU-A102 | E4: =XLOOKUP(D4,產品規格主檔!$A$3:$A$8,產品規格主檔!$B$3:$B$8) | F4: 1 | G4: 3880 | H4: =F4*G4 | I4: =XLOOKUP(D4,產品規格主檔!$A$3:$A$8,產品規格主檔!$E$3:$E$8) | J4: =F4*I4 | K4: =H4-J4 | L4: =K4/H4 | M4: 正常完成 | N4: 現場刷卡
A5: ORD-2026-003 | B5: 2026-01-10 | C5: Momo購物網 | D5: SKU-B201 | E5: =XLOOKUP(D5,產品規格主檔!$A$3:$A$8,產品規格主檔!$B$3:$B$8) | F5: 2 | G5: 2280 | H5: =F5*G5 | I5: =XLOOKUP(D5,產品規格主檔!$A$3:$A$8,產品規格主檔!$E$3:$E$8) | J5: =F5*I5 | K5: =H5-J5 | L5: =K5/H5 | M5: 正常完成 | N5: 年貨節活動
A6: ORD-2026-004 | B6: 2026-01-14 | C6: 蝦皮商城 | D6: SKU-C301 | E6: =XLOOKUP(D6,產品規格主檔!$A$3:$A$8,產品規格主檔!$B$3:$B$8) | F6: 5 | G6: 890 | H6: =F6*G6 | I6: =XLOOKUP(D6,產品規格主檔!$A$3:$A$8,產品規格主檔!$E$3:$E$8) | J6: =F6*I6 | K6: =H6-J6 | L6: =K6/H6 | M6: 正常完成 | N6: 折價券折抵
A7: ORD-2026-005 | B7: 2026-01-18 | C7: 台中旗艦門市 | D7: SKU-A102 | E7: =XLOOKUP(D7,產品規格主檔!$A$3:$A$8,產品規格主檔!$B$3:$B$8) | F7: 2 | G7: 3880 | H7: =F7*G7 | I7: =XLOOKUP(D7,產品規格主檔!$A$3:$A$8,產品規格主檔!$E$3:$E$8) | J7: =F7*I7 | K7: =H7-J7 | L7: =K7/H7 | M7: 正常完成 | N7: VIP客戶
A8: ORD-2026-006 | B8: 2026-01-22 | C8: 官網商城 | D8: SKU-B202 | E8: =XLOOKUP(D8,產品規格主檔!$A$3:$A$8,產品規格主檔!$B$3:$B$8) | F8: 1 | G8: 4500 | H8: =F8*G8 | I8: =XLOOKUP(D8,產品規格主檔!$A$3:$A$8,產品規格主檔!$E$3:$E$8) | J8: =F8*I8 | K8: =H8-J8 | L8: =K8/H8 | M8: 已退貨 | N8: 尺寸不合退換
A9: ORD-2026-007 | B9: 2026-01-28 | C9: Momo購物網 | D9: SKU-A101 | E9: =XLOOKUP(D9,產品規格主檔!$A$3:$A$8,產品規格主檔!$B$3:$B$8) | F9: 4 | G9: 1580 | H9: =F9*G9 | I9: =XLOOKUP(D9,產品規格主檔!$A$3:$A$8,產品規格主檔!$E$3:$E$8) | J9: =F9*I9 | K9: =H9-J9 | L9: =K9/H9 | M9: 正常完成 | N9: 整箱採購
A10: ORD-2026-008 | B10: 2026-02-03 | C10: 台北信義門市 | D10: SKU-B201 | E10: =XLOOKUP(D10,產品規格主檔!$A$3:$A$8,產品規格主檔!$B$3:$B$8) | F10: 3 | G10: 2280 | H10: =F10*G10 | I10: =XLOOKUP(D10,產品規格主檔!$A$3:$A$8,產品規格主檔!$E$3:$E$8) | J10: =F10*I10 | K10: =H10-J10 | L10: =K10/H10 | M10: 正常完成 | N10: 現場提貨
A11: ORD-2026-009 | B11: 2026-02-09 | C11: 蝦皮商城 | D11: SKU-C302 | E11: =XLOOKUP(D11,產品規格主檔!$A$3:$A$8,產品規格主檔!$B$3:$B$8) | F11: 2 | G11: 1250 | H11: =F11*G11 | I11: =XLOOKUP(D11,產品規格主檔!$A$3:$A$8,產品規格主檔!$E$3:$E$8) | J11: =F11*I11 | K11: =H11-J11 | L11: =K11/H11 | M11: 已退貨 | N11: 商品外箱破損
A12: ORD-2026-010 | B12: 2026-02-14 | C12: 官網商城 | D12: SKU-A102 | E12: =XLOOKUP(D12,產品規格主檔!$A$3:$A$8,產品規格主檔!$B$3:$B$8) | F12: 1 | G12: 3880 | H12: =F12*G12 | I12: =XLOOKUP(D12,產品規格主檔!$A$3:$A$8,產品規格主檔!$E$3:$E$8) | J12: =F12*I12 | K12: =H12-J12 | L12: =K12/H12 | M12: 正常完成 | N12: 情人節活動
A13: ORD-2026-011 | B13: 2026-02-18 | C13: 台中旗艦門市 | D13: SKU-B202 | E13: =XLOOKUP(D13,產品規格主檔!$A$3:$A$8,產品規格主檔!$B$3:$B$8) | F13: 2 | G13: 4500 | H13: =F13*G13 | I13: =XLOOKUP(D13,產品規格主檔!$A$3:$A$8,產品規格主檔!$E$3:$E$8) | J13: =F13*I13 | K13: =H13-J13 | L13: =K13/H13 | M13: 正常完成 | N13: 新品體驗
A14: ORD-2026-012 | B14: 2026-02-23 | C14: Momo購物網 | D14: SKU-C301 | E14: =XLOOKUP(D14,產品規格主檔!$A$3:$A$8,產品規格主檔!$B$3:$B$8) | F14: 10 | G14: 890 | H14: =F14*G14 | I14: =XLOOKUP(D14,產品規格主檔!$A$3:$A$8,產品規格主檔!$E$3:$E$8) | J14: =F14*I14 | K14: =H14-J14 | L14: =K14/H14 | M14: 正常完成 | N14: 企業採購
... A22: ORD-2026-020 | B22: 2026-03-31 | C22: Momo購物網 | D22: SKU-B201 | E22: =XLOOKUP(D22,產品規格主檔!$A$3:$A$8,產品規格主檔!$B$3:$B$8) | F22: 4 | G22: 2280 | H22: =F22*G22 | I22: =XLOOKUP(D22,產品規格主檔!$A$3:$A$8,產品規格主檔!$E$3:$E$8) | J22: =F22*I22 | K22: =H22-J22 | L22: =K22/H22 | M22: 正常完成 | N22: 季末大促
A23: 合計總算 | F23: =SUM(F3:F22) | H23: =SUM(H3:H22) | J23: =SUM(J3:J22) | K23: =SUM(K3:K22) | L23: =K23/H23 | M23: ="退貨: " & COUNTIF(M3:M22,"已退貨") & " 筆"
